pyinfra_prometheus/__init__.py
pyinfra_prometheus/defaults.py
pyinfra_prometheus/generic_exporter.py
pyinfra_prometheus/node_exporter.py
pyinfra_prometheus/prometheus.py
pyinfra_prometheus/util.py
pyinfra_prometheus/templates/exporter.service.j2
pyinfra_prometheus/templates/init.d.j2
pyinfra_prometheus/templates/node_exporter.service.j2
pyinfra_prometheus/templates/prometheus.service.j2
pyinfra_prometheus/templates/prometheus.yml.j2
pyinfra_prometheus-0.5.dist-info/DESCRIPTION.rst
pyinfra_prometheus-0.5.dist-info/METADATA
pyinfra_prometheus-0.5.dist-info/RECORD
pyinfra_prometheus-0.5.dist-info/WHEEL
pyinfra_prometheus-0.5.dist-info/metadata.json
pyinfra_prometheus-0.5.dist-info/top_level.txt
