Metadata-Version: 2.0
Name: pyinfra-prometheus
Version: 0.5
Summary: Install & bootstrap prometheus clusters with pyinfra.
Home-page: https://github.com/grantstephens/pyinfra-prometheus
Author: UNKNOWN
Author-email: UNKNOWN
License: MIT
Platform: UNKNOWN
Requires-Dist: pyinfra (>=0.5)
